LICENSE
MANIFEST.in
README.rst
requirements.txt
setup.py
tox.ini
nosenicedots/__init__.py
nosenicedots/plugin.py
nosenicedots.egg-info/PKG-INFO
nosenicedots.egg-info/SOURCES.txt
nosenicedots.egg-info/dependency_links.txt
nosenicedots.egg-info/entry_points.txt
nosenicedots.egg-info/requires.txt
nosenicedots.egg-info/top_level.txt
nosenicedots/tests/__init__.py
nosenicedots/tests/test_functional.py
nosenicedots/tests/test_units.py