Metadata-Version: 1.1
Name: nosenicedots
Version: 0.5
Summary: Nose plugin that prints nicer dots grouped by class/module.
Home-page: https://github.com/kumar303/nose-nicedots/
Author: Kumar McMillan
Author-email: kumar.mcmillan@gmail.com
License: Apache License
Platform: UNKNOWN
Classifier: Intended Audience :: Developers
Classifier: Natural Language :: English
Classifier: Operating System :: OS Independent
Classifier: Topic :: Software Development :: Testing
Classifier: Programming Language :: Python :: 2
